physics_x_optics_cbse/__init__.py
physics_x_optics_cbse/constants.py
physics_x_optics_cbse/lenses.py
physics_x_optics_cbse/reflection.py
physics_x_optics_cbse/refraction.py
physics_x_optics_cbse-1.0.2.dist-info/licenses/LICENSE.txt
physics_x_optics_cbse-1.0.2.dist-info/METADATA
physics_x_optics_cbse-1.0.2.dist-info/WHEEL
physics_x_optics_cbse-1.0.2.dist-info/top_level.txt
physics_x_optics_cbse-1.0.2.dist-info/RECORD
