Metadata-Version: 2.4
Name: physics_x_optics_cbse
Version: 1.0.2
Summary: Class 10 CBSE Optics Helper Library
Home-page: https://github.com/dineshlabx/physics_x_optics_cbse
Author: Dinesh_Pandiyan_B
Author-email: rajadineshp@gmail.com
Project-URL: source code, https://github.com/dineshlabx/physics_x_optics_cbse
Project-URL: Bug Tracker, https://github.com/dineshlabx/physics_x_optics_cbse
License-File: LICENSE.txt
Dynamic: author
Dynamic: author-email
Dynamic: description
Dynamic: description-content-type
Dynamic: home-page
Dynamic: license-file
Dynamic: project-url
Dynamic: summary
